{"quests":[{"races":[2,5,6,9,10,26,27,28,35,36],"questID":13708},{"g":[{"itemID":154992}],"lvl":[60],"questID":47148},{"g":[{"itemID":161475}],"questID":51355},{"lvl":[35],"questID":53583},{"lvl":[35],"questID":53602},{"lvl":[60],"questID":55424},{"lvl":[60],"questID":56070},{"g":[{"itemID":183744}],"questID":56470},{"lvl":[58],"questID":56829},{"lvl":[58],"questID":56942},{"lvl":[58],"questID":56955},{"lvl":[58],"questID":56978},{"lvl":[58],"questID":57007},{"lvl":[58],"questID":57025},{"lvl":[58],"questID":57026},{"lvl":[59],"questID":57098},{"lvl":[58],"questID":57099},{"lvl":[58],"questID":57100},{"lvl":[51],"questID":57102},{"g":[{"itemID":181291}],"questID":57117},{"lvl":[51],"questID":57125},{"lvl":[59],"questID":57131},{"lvl":[59],"questID":57136},{"lvl":[59],"questID":57159},{"lvl":[58],"questID":57161},{"lvl":[59],"questID":57164},{"lvl":[58],"questID":57172},{"lvl":[58],"questID":57173},{"lvl":[58],"questID":57174},{"lvl":[58],"questID":57175},{"lvl":[58],"questID":57176},{"lvl":[58],"questID":57178},{"lvl":[58],"questID":57179},{"lvl":[58],"questID":57180},{"lvl":[58],"questID":57182},{"lvl":[58],"questID":57185},{"lvl":[59],"questID":57189},{"lvl":[59],"questID":57190},{"lvl":[58],"questID":57228},{"lvl":[59],"questID":57240},{"lvl":[53],"questID":57245},{"lvl":[51],"questID":57261},{"lvl":[53],"questID":57278},{"lvl":[53],"questID":57284},{"lvl":[54],"questID":57301},{"g":[{"itemID":176285},{"itemID":176284},{"itemID":176283},{"itemID":176278},{"itemID":181529},{"itemID":176277},{"itemID":176280},{"itemID":181531},{"itemID":176444},{"itemID":176282},{"itemID":176286},{"itemID":176281},{"itemID":176279},{"itemID":181534}],"lvl":[53],"questID":57316},{"lvl":[59],"questID":57380},{"lvl":[58],"questID":57381},{"lvl":[53],"questID":57386},{"lvl":[53],"questID":57390},{"lvl":[59],"questID":57405},{"lvl":[58],"questID":57414},{"lvl":[53],"questID":57425},{"lvl":[59],"questID":57426},{"lvl":[59],"questID":57427},{"lvl":[59],"questID":57428},{"lvl":[59],"questID":57442},{"lvl":[59],"questID":57460},{"g":[{"itemID":179990},{"itemID":179989},{"itemID":179988},{"itemID":179991}],"lvl":[59],"questID":57461},{"lvl":[58],"questID":57471},{"lvl":[58],"questID":57474},{"lvl":[58],"questID":57477},{"lvl":[58],"questID":57481},{"lvl":[53],"questID":57511},{"lvl":[53],"questID":57512},{"lvl":[53],"questID":57513},{"lvl":[54],"questID":57514},{"lvl":[53],"questID":57515},{"lvl":[54],"questID":57516},{"lvl":[52],"questID":57529},{"lvl":[59],"questID":57531},{"lvl":[59],"questID":57532},{"lvl":[59],"questID":57533},{"lvl":[59],"questID":57534},{"lvl":[59],"questID":57535},{"lvl":[59],"questID":57536},{"lvl":[53],"questID":57537},{"lvl":[52],"questID":57538},{"lvl":[52],"questID":57545},{"lvl":[52],"questID":57547},{"g":[{"itemID":175617},{"itemID":175619},{"itemID":175616},{"itemID":175618}],"lvl":[52],"questID":57568},{"lvl":[59],"questID":57571},{"lvl":[51],"questID":57584},{"g":[{"itemID":183744}],"questID":57634},{"lvl":[56],"questID":57651},{"lvl":[56],"questID":57652},{"lvl":[56],"questID":57653},{"lvl":[56],"questID":57655},{"lvl":[56],"questID":57656},{"lvl":[56],"questID":57657},{"lvl":[60],"questID":57661},{"lvl":[51],"questID":57676},{"lvl":[51],"questID":57677},{"lvl":[59],"questID":57689},{"lvl":[59],"questID":57690},{"lvl":[59],"questID":57691},{"lvl":[58],"questID":57692},{"lvl":[59],"questID":57693},{"lvl":[59],"questID":57694},{"g":[{"itemID":184326},{"itemID":184320},{"itemID":177635},{"itemID":177642},{"itemID":177641},{"itemID":177643},{"itemID":177639},{"itemID":177644},{"itemID":177638},{"itemID":177637},{"itemID":177636}],"lvl":[59],"questID":57724},{"lvl":[55],"questID":57787},{"lvl":[56],"questID":57816},{"lvl":[56],"questID":57818},{"lvl":[56],"questID":57824},{"lvl":[56],"questID":57825},{"lvl":[56],"questID":57865},{"lvl":[56],"questID":57866},{"lvl":[56],"questID":57867},{"lvl":[56],"questID":57868},{"lvl":[56],"questID":57869},{"lvl":[56],"questID":57870},{"lvl":[56],"questID":57871},{"questID":57901,"lvl":[60],"_category":"Covenant Sanctum"},{"lvl":[54],"questID":57912},{"lvl":[58],"questID":57918},{"lvl":[58],"questID":57919},{"lvl":[58],"questID":57920},{"lvl":[58],"questID":57921},{"lvl":[58],"questID":57922},{"lvl":[58],"questID":57923},{"lvl":[58],"questID":57924},{"lvl":[58],"questID":57925},{"lvl":[58],"questID":57926},{"lvl":[58],"questID":57927},{"lvl":[58],"questID":57928},{"lvl":[58],"questID":57929},{"lvl":[55],"questID":57947},{"lvl":[55],"questID":57948},{"lvl":[55],"questID":57949},{"lvl":[55],"questID":57950},{"lvl":[55],"questID":57951},{"lvl":[56],"questID":57952},{"lvl":[54],"questID":57976},{"lvl":[54],"questID":57978},{"lvl":[54],"questID":57979},{"lvl":[54],"questID":57982},{"lvl":[54],"questID":57983},{"lvl":[54],"questID":57984},{"lvl":[54],"questID":57985},{"lvl":[54],"questID":57986},{"lvl":[54],"questID":57987},{"lvl":[54],"questID":57993},{"lvl":[54],"questID":57994},{"lvl":[54],"questID":58011},{"lvl":[54],"questID":58016},{"lvl":[56],"questID":58022},{"lvl":[56],"questID":58023},{"lvl":[56],"questID":58024},{"lvl":[56],"questID":58025},{"lvl":[56],"questID":58026},{"lvl":[54],"questID":58027},{"lvl":[54],"questID":58031},{"lvl":[54],"questID":58036},{"lvl":[54],"questID":58045},{"lvl":[60],"questID":58060},{"lvl":[60],"questID":58062},{"lvl":[58],"questID":58067},{"lvl":[54],"questID":58068},{"lvl":[58],"questID":58069},{"lvl":[58],"questID":58070},{"lvl":[58],"questID":58071},{"lvl":[58],"questID":58072},{"lvl":[58],"questID":58073},{"lvl":[58],"questID":58074},{"lvl":[58],"questID":58075},{"lvl":[58],"questID":58077},{"lvl":[58],"questID":58078},{"lvl":[58],"questID":58079},{"lvl":[58],"questID":58080},{"lvl":[58],"questID":58081},{"lvl":[60],"questID":58086},{"lvl":[53],"questID":58088},{"lvl":[54],"questID":58090},{"g":[{"itemID":184717}],"lvl":[58],"questID":58092},{"lvl":[58],"questID":58093},{"g":[{"itemID":181646}],"questID":58095},{"lvl":[58],"questID":58127},{"lvl":[58],"questID":58128},{"lvl":[58],"questID":58129},{"lvl":[56],"questID":58161},{"lvl":[56],"questID":58162},{"g":[{"itemID":183851}],"lvl":[56],"questID":58163},{"lvl":[56],"questID":58164},{"lvl":[56],"questID":58165},{"g":[{"itemID":175675},{"itemID":175678},{"itemID":175676},{"itemID":175677}],"lvl":[56],"questID":58166},{"lvl":[57],"questID":58264},{"lvl":[57],"questID":58265},{"lvl":[57],"questID":58266},{"lvl":[57],"questID":58267},{"lvl":[54],"questID":58268},{"lvl":[58],"questID":58272},{"lvl":[58],"questID":58328},{"lvl":[58],"questID":58338},{"lvl":[54],"questID":58351},{"lvl":[58],"questID":58396},{"lvl":[58],"questID":58397},{"lvl":[58],"questID":58400},{"lvl":[58],"questID":58401},{"lvl":[58],"questID":58402},{"lvl":[58],"questID":58403},{"lvl":[58],"questID":58404},{"lvl":[58],"questID":58405},{"g":[{"itemID":180948}],"questID":58407},{"lvl":[54],"questID":58431},{"g":[{"itemID":183744}],"questID":58432},{"lvl":[58],"questID":58433},{"g":[{"itemID":181913},{"itemID":179769},{"itemID":179891},{"itemID":175592}],"questID":58452},{"_type":"Group","questID":58454},{"lvl":[57],"questID":58480},{"lvl":[57],"questID":58483},{"lvl":[57],"questID":58484},{"lvl":[57],"questID":58486},{"lvl":[57],"questID":58488},{"g":[{"itemID":183744}],"questID":58515},{"lvl":[51],"questID":58516},{"lvl":[51],"questID":58517},{"lvl":[57],"questID":58524},{"g":[{"itemID":183744}],"questID":58525},{"lvl":[54],"questID":58575},{"lvl":[58],"questID":58589},{"lvl":[58],"questID":58590},{"lvl":[58],"questID":58591},{"lvl":[58],"questID":58592},{"lvl":[58],"questID":58607},{"_category":"Covenant Sanctum","questID":58609},{"lvl":[54],"questID":58616},{"lvl":[54],"questID":58617},{"lvl":[54],"questID":58618},{"lvl":[54],"questID":58619},{"lvl":[54],"questID":58620},{"lvl":[54],"questID":58621},{"lvl":[54],"questID":58622},{"lvl":[54],"questID":58623},{"lvl":[58],"questID":58644},{"lvl":[58],"questID":58654},{"lvl":[50],"questID":58672},{"lvl":[50],"questID":58673},{"lvl":[50],"questID":58674},{"lvl":[50],"questID":58675},{"lvl":[58],"questID":58714},{"lvl":[60],"questID":58717},{"lvl":[58],"questID":58719},{"lvl":[58],"questID":58720},{"lvl":[58],"questID":58721},{"lvl":[58],"questID":58723},{"lvl":[58],"questID":58724},{"lvl":[60],"questID":58725},{"lvl":[54],"questID":58726},{"lvl":[53],"questID":58750},{"lvl":[54],"questID":58751},{"lvl":[52],"questID":58771},{"lvl":[53],"questID":58785},{"g":[{"itemID":178161},{"itemID":177058},{"itemID":179948},{"itemID":174297}],"questID":58789},{"lvl":[53],"questID":58794},{"g":[{"itemID":181743}],"questID":58798},{"lvl":[52],"questID":58799},{"lvl":[52],"questID":58800},{"lvl":[54],"questID":58821},{"lvl":[52],"questID":58843},{"lvl":[58],"questID":58855},{"lvl":[58],"questID":58869},{"lvl":[54],"questID":58900},{"lvl":[59],"questID":58916},{"lvl":[58],"questID":58931},{"lvl":[58],"questID":58932},{"lvl":[58],"questID":58936},{"lvl":[59],"questID":58941},{"lvl":[54],"questID":58947},{"lvl":[52],"questID":58976},{"lvl":[52],"questID":58977},{"lvl":[52],"questID":58978},{"lvl":[52],"questID":58979},{"lvl":[52],"questID":58980},{"g":[{"itemID":183744}],"questID":58992},{"lvl":[58],"questID":58996},{"lvl":[54],"questID":59009},{"g":[{"itemID":180672},{"itemID":180667},{"itemID":180665},{"itemID":180790},{"itemID":180669},{"itemID":180671},{"itemID":180670},{"itemID":180668},{"itemID":180791},{"itemID":180663},{"itemID":180666},{"itemID":180664},{"itemID":180792},{"itemID":180673}],"questID":59011},{"lvl":[59],"questID":59014},{"lvl":[58],"questID":59021},{"lvl":[58],"questID":59023},{"lvl":[54],"questID":59025},{"g":[{"itemID":183744}],"questID":59043},{"g":[{"itemID":183744}],"questID":59126},{"lvl":[54],"questID":59130},{"lvl":[53],"questID":59171},{"lvl":[54],"questID":59172},{"lvl":[54],"questID":59185},{"lvl":[54],"questID":59188},{"lvl":[54],"questID":59190},{"lvl":[52],"questID":59196},{"lvl":[52],"questID":59197},{"lvl":[52],"questID":59198},{"lvl":[52],"questID":59199},{"lvl":[52],"questID":59200},{"lvl":[55],"questID":59206},{"lvl":[59],"questID":59209},{"lvl":[54],"questID":59210},{"lvl":[54],"questID":59223},{"lvl":[54],"questID":59231},{"lvl":[58],"questID":59232},{"g":[{"itemID":179765},{"itemID":175576},{"itemID":179774},{"itemID":181979},{"itemID":179657},{"itemID":179888},{"itemID":181909}],"questID":59242},{"lvl":[59],"questID":59256},{"g":[{"itemID":183744}],"questID":59293},{"g":[{"itemID":180839}],"questID":59311},{"lvl":[59],"questID":59327},{"lvl":[52],"questID":59426},{"lvl":[59],"questID":59427},{"lvl":[54],"questID":59430},{"_category":"Dungeon","g":[{"itemID":175533},{"itemID":175532},{"itemID":175534},{"itemID":175531}],"lvl":[54],"questID":59520},{"g":[{"itemID":182077}],"questID":59555},{"lvl":[58],"questID":59604},{"lvl":[58],"questID":59605},{"lvl":[58],"questID":59607},{"lvl":[54],"questID":59616},{"lvl":[56],"questID":59621},{"lvl":[56],"questID":59622},{"lvl":[56],"questID":59623},{"lvl":[56],"questID":59656},{"lvl":[58],"questID":59710},{"lvl":[58],"questID":59712},{"lvl":[58],"questID":59713},{"lvl":[58],"questID":59714},{"lvl":[58],"questID":59715},{"lvl":[58],"questID":59716},{"lvl":[58],"questID":59724},{"lvl":[58],"questID":59726},{"lvl":[58],"questID":59740},{"lvl":[54],"questID":59750},{"lvl":[51],"questID":59773},{"lvl":[51],"questID":59774},{"lvl":[54],"questID":59781},{"lvl":[54],"questID":59800},{"lvl":[56],"questID":59801},{"lvl":[56],"questID":59802},{"_type":"Group","lvl":[60],"questID":59826},{"_type":"Group","lvl":[60],"questID":59827},{"_type":"Group","lvl":[60],"questID":59828},{"lvl":[54],"questID":59837},{"lvl":[58],"questID":59846},{"lvl":[58],"questID":59868},{"lvl":[54],"questID":59879},{"lvl":[54],"questID":59882},{"g":[{"itemID":175517},{"itemID":175519},{"itemID":175518},{"itemID":175516}],"lvl":[54],"questID":59994},{"lvl":[58],"questID":60001},{"lvl":[53],"questID":60005},{"lvl":[53],"questID":60006},{"lvl":[53],"questID":60007},{"lvl":[53],"questID":60008},{"lvl":[53],"questID":60009},{"lvl":[52],"questID":60013},{"lvl":[53],"questID":60020},{"lvl":[53],"questID":60021},{"g":[{"itemID":178061}],"questID":60041},{"lvl":[53],"questID":60052},{"lvl":[53],"questID":60053},{"lvl":[53],"questID":60054},{"lvl":[53],"questID":60055},{"lvl":[53],"questID":60056},{"g":[{"itemID":184712},{"itemID":184713},{"itemID":184714},{"itemID":184715}],"questID":60057},{"lvl":[58],"questID":60060},{"lvl":[60],"questID":60061},{"lvl":[60],"questID":60062},{"lvl":[60],"questID":60063},{"lvl":[60],"questID":60064},{"lvl":[60],"questID":60065},{"lvl":[60],"questID":60066},{"lvl":[60],"questID":60092},{"lvl":[60],"questID":60099},{"lvl":[60],"questID":60100},{"lvl":[60],"questID":60101},{"lvl":[60],"questID":60102},{"lvl":[60],"questID":60103},{"lvl":[60],"questID":60104},{"lvl":[60],"questID":60105},{"lvl":[60],"questID":60106},{"lvl":[60],"questID":60107},{"lvl":[58],"questID":60127},{"lvl":[58],"questID":60128},{"lvl":[58],"questID":60147},{"isDaily":1,"questID":60153},{"lvl":[58],"questID":60159},{"lvl":[58],"questID":60160},{"lvl":[58],"questID":60164},{"lvl":[58],"questID":60165},{"isDaily":1,"questID":60175},{"lvl":[58],"questID":60176},{"lvl":[58],"questID":60177},{"lvl":[58],"questID":60178},{"lvl":[53],"questID":60179},{"lvl":[52],"questID":60180},{"lvl":[53],"questID":60181},{"isDaily":1,"questID":60188},{"g":[{"itemID":183830}],"questID":60195},{"lvl":[58],"questID":60227},{"lvl":[58],"questID":60228},{"g":[{"itemID":183744}],"questID":60237},{"g":[{"itemID":184374}],"lvl":[60],"questID":60242},{"g":[{"itemID":184374}],"questID":60243},{"g":[{"itemID":184374}],"lvl":[60],"questID":60244},{"g":[{"itemID":184374}],"questID":60245},{"g":[{"itemID":184374}],"lvl":[60],"questID":60246},{"g":[{"itemID":184374}],"questID":60247},{"g":[{"itemID":184374}],"lvl":[60],"questID":60248},{"g":[{"itemID":184374}],"questID":60249},{"g":[{"itemID":184374}],"_type":"Dungeon","questID":60250},{"g":[{"itemID":184374}],"_type":"Dungeon","questID":60251},{"g":[{"itemID":184374}],"_type":"Dungeon","questID":60252},{"g":[{"itemID":184374}],"_type":"Dungeon","questID":60253},{"g":[{"itemID":184374}],"_type":"Dungeon","questID":60254},{"g":[{"itemID":184374}],"_type":"Dungeon","questID":60255},{"_type":"Dungeon","questID":60256},{"g":[{"itemID":184374}],"_type":"Dungeon","questID":60257},{"_type":"Legendary","lvl":[60],"questID":60267},{"_type":"Legendary","lvl":[60],"questID":60268},{"_type":"Legendary","lvl":[60],"questID":60269},{"_type":"Legendary","lvl":[60],"questID":60270},{"_type":"Legendary","lvl":[60],"questID":60271},{"_type":"Legendary","lvl":[60],"questID":60272},{"lvl":[60],"questID":60275},{"lvl":[59],"questID":60276},{"lvl":[58],"questID":60277},{"lvl":[60],"questID":60279},{"g":[{"itemID":183744}],"questID":60291},{"lvl":[59],"questID":60313},{"lvl":[52],"questID":60315},{"lvl":[55],"questID":60338},{"g":[{"itemID":183744}],"questID":60340},{"lvl":[55],"questID":60341},{"g":[{"itemID":183744}],"questID":60342},{"lvl":[54],"questID":60428},{"lvl":[54],"questID":60451},{"lvl":[54],"questID":60453},{"lvl":[54],"questID":60461},{"lvl":[51],"questID":60466},{"lvl":[59],"questID":60467},{"lvl":[59],"questID":60468},{"lvl":[59],"questID":60469},{"lvl":[59],"questID":60470},{"lvl":[58],"questID":60480},{"lvl":[58],"questID":60487},{"_category":"Path of Ascension","questID":60489},{"_category":"Path of Ascension","questID":60493},{"_category":"Path of Ascension","questID":60494},{"_category":"Path of Ascension","questID":60495},{"_category":"Path of Ascension","questID":60496},{"_category":"Path of Ascension","questID":60497},{"_category":"Path of Ascension","questID":60498},{"g":[{"itemID":181552}],"questID":60501},{"g":[{"itemID":181549}],"questID":60502},{"lvl":[59],"questID":60506},{"lvl":[58],"questID":60509},{"lvl":[58],"questID":60514},{"lvl":[58],"questID":60517},{"lvl":[56],"questID":60519},{"lvl":[56],"questID":60520},{"lvl":[56],"questID":60521},{"lvl":[56],"questID":60522},{"lvl":[54],"questID":60557},{"lvl":[56],"questID":60563},{"lvl":[59],"questID":60566},{"lvl":[56],"questID":60567},{"lvl":[58],"questID":60568},{"lvl":[58],"questID":60572},{"lvl":[56],"questID":60575},{"lvl":[56],"questID":60577},{"lvl":[58],"questID":60578},{"lvl":[56],"questID":60594},{"lvl":[58],"questID":60599},{"lvl":[56],"questID":60600},{"lvl":[58],"questID":60621},{"lvl":[56],"questID":60624},{"lvl":[56],"questID":60628},{"lvl":[56],"questID":60629},{"lvl":[56],"questID":60630},{"lvl":[56],"questID":60631},{"lvl":[56],"questID":60632},{"lvl":[56],"questID":60637},{"lvl":[56],"questID":60638},{"lvl":[56],"questID":60639},{"lvl":[56],"questID":60647},{"lvl":[56],"questID":60648},{"lvl":[60],"questID":60651},{"lvl":[58],"questID":60661},{"lvl":[56],"questID":60671},{"lvl":[56],"questID":60709},{"lvl":[56],"questID":60724},{"lvl":[54],"questID":60733},{"lvl":[51],"questID":60735},{"lvl":[57],"questID":60738},{"lvl":[55],"questID":60763},{"lvl":[57],"questID":60764},{"g":[{"itemID":183744}],"questID":60765},{"lvl":[55],"questID":60778},{"lvl":[54],"questID":60831},{"lvl":[55],"questID":60857},{"lvl":[55],"questID":60859},{"lvl":[54],"questID":60886},{"_category":"Timewalking Campaign","questID":60887},{"lvl":[58],"questID":60889},{"_category":"Timewalking Campaign","questID":60891},{"lvl":[54],"questID":60900},{"_category":"Path of Ascension","questID":60907},{"_category":"Path of Ascension","questID":60945},{"_category":"Path of Ascension","questID":60946},{"_category":"Path of Ascension","questID":60947},{"_category":"Timewalking Campaign","questID":60959},{"_category":"Timewalking Campaign","questID":60961},{"_category":"Timewalking Campaign","questID":60962},{"_category":"Timewalking Campaign","questID":60963},{"_category":"Timewalking Campaign","questID":60964},{"_category":"Timewalking Campaign","questID":60965},{"_category":"Timewalking Campaign","questID":60968},{"_category":"Timewalking Campaign","questID":60969},{"_category":"Timewalking Campaign","questID":60970},{"_category":"Timewalking Campaign","questID":60971},{"_category":"Path of Ascension","questID":60973},{"questID":60974,"lvl":[60],"_category":"Path of Ascension"},{"_category":"Path of Ascension","questID":60975},{"lvl":[56],"questID":61051},{"lvl":[58],"questID":61087},{"lvl":[53],"questID":61096},{"g":[{"itemID":184757}],"questID":61099},{"lvl":[53],"questID":61107},{"lvl":[60],"questID":61217},{"lvl":[60],"questID":61218},{"lvl":[60],"questID":61219},{"lvl":[60],"questID":61221},{"lvl":[60],"questID":61222},{"lvl":[60],"questID":61223},{"_category":"Path of Ascension","questID":61265},{"_category":"Path of Ascension","questID":61269},{"_category":"Path of Ascension","questID":61272},{"_category":"Path of Ascension","questID":61304},{"lvl":[60],"questID":61313},{"lvl":[60],"questID":61314},{"lvl":[60],"questID":61317},{"lvl":[60],"questID":61318},{"lvl":[60],"questID":61319},{"lvl":[60],"questID":61320},{"lvl":[60],"questID":61321},{"g":[{"itemID":182283},{"itemID":182265},{"itemID":182274},{"itemID":182256}],"questID":61323},{"lvl":[60],"questID":61331},{"lvl":[60],"questID":61332},{"lvl":[60],"questID":61333},{"_category":"Path of Ascension","questID":61356},{"_category":"Path of Ascension","questID":61357},{"_category":"Path of Ascension","questID":61358},{"_category":"Path of Ascension","questID":61360},{"_category":"Path of Ascension","questID":61361},{"_category":"Path of Ascension","questID":61362},{"_category":"Path of Ascension","questID":61363},{"_category":"Path of Ascension","questID":61364},{"_category":"Path of Ascension","questID":61365},{"_category":"Path of Ascension","questID":61366},{"_category":"Path of Ascension","questID":61367},{"_category":"Path of Ascension","questID":61368},{"_category":"Path of Ascension","questID":61369},{"_category":"Path of Ascension","questID":61370},{"_category":"Path of Ascension","questID":61371},{"_category":"Path of Ascension","questID":61372},{"_category":"Path of Ascension","questID":61373},{"lvl":[60],"questID":61421},{"lvl":[60],"questID":61422},{"lvl":[60],"questID":61423},{"lvl":[60],"questID":61424},{"lvl":[60],"questID":61425},{"lvl":[60],"questID":61426},{"lvl":[58],"questID":61432},{"_category":"Path of Ascension","questID":61436},{"_category":"Path of Ascension","questID":61473},{"_category":"Path of Ascension","questID":61478},{"_category":"Path of Ascension","questID":61489},{"_category":"Path of Ascension","questID":61490},{"g":[{"itemID":183744}],"questID":61509},{"g":[{"itemID":183744}],"questID":61510},{"g":[{"itemID":183744}],"questID":61511},{"g":[{"itemID":183744}],"questID":61522},{"g":[{"itemID":183744}],"questID":61523},{"_category":"Path of Ascension","questID":61713},{"questID":61714,"lvl":[60],"_category":"Path of Ascension"},{"g":[{"itemID":184165}],"questID":61716},{"_type":"Group","questID":61765},{"lvl":[60],"questID":61957},{"lvl":[60],"questID":61958},{"lvl":[60],"questID":61959},{"lvl":[60],"questID":61960},{"lvl":[60],"questID":61961},{"lvl":[60],"questID":61962},{"_category":"Path of Ascension","questID":61963},{"_category":"Path of Ascension","questID":61965},{"lvl":[60],"questID":61982},{"g":[{"itemID":183744}],"questID":61996},{"g":[{"itemID":183744}],"questID":62041},{"_category":"Path of Ascension","questID":62052},{"_category":"Path of Ascension","questID":62053},{"lvl":[60],"questID":62074},{"lvl":[53],"questID":62085},{"lvl":[60],"questID":62086},{"lvl":[60],"questID":62088},{"lvl":[60],"questID":62089},{"lvl":[60],"questID":62090},{"lvl":[60],"questID":62091},{"lvl":[60],"questID":62092},{"lvl":[60],"questID":62093},{"lvl":[60],"questID":62096},{"lvl":[60],"questID":62097},{"lvl":[60],"questID":62098},{"lvl":[60],"questID":62099},{"lvl":[60],"questID":62100},{"lvl":[60],"questID":62101},{"lvl":[60],"questID":62102},{"lvl":[60],"questID":62103},{"lvl":[53],"questID":62168},{"lvl":[52],"questID":62170},{"lvl":[58],"questID":62182},{"lvl":[58],"questID":62183},{"lvl":[58],"questID":62184},{"lvl":[58],"questID":62189},{"g":[{"itemID":183744}],"questID":62194},{"g":[{"itemID":183744}],"questID":62195},{"lvl":[52],"questID":62200},{"g":[{"itemID":183744}],"questID":62213},{"_type":"Group","questID":62214},{"g":[{"itemID":183744}],"questID":62216},{"g":[{"itemID":183744}],"questID":62217},{"_category":"Path of Ascension","questID":62218},{"_category":"Path of Ascension","questID":62219},{"_category":"Path of Ascension","questID":62223},{"g":[{"itemID":183744}],"questID":62232},{"_type":"Group","questID":62234},{"g":[{"itemID":183744}],"questID":62244},{"g":[{"itemID":183744}],"questID":62256},{"g":[{"itemID":183744}],"questID":62261},{"isDaily":1,"questID":62263},{"g":[{"itemID":183744}],"questID":62276},{"g":[{"itemID":184315}],"questID":62284},{"g":[{"itemID":184315}],"questID":62285},{"g":[{"itemID":184315}],"questID":62286},{"g":[{"itemID":184315}],"questID":62287},{"g":[{"itemID":184315}],"questID":62288},{"g":[{"itemID":184374}],"questID":62289},{"g":[{"itemID":183744}],"questID":62294},{"isDaily":1,"questID":62296},{"_category":"Dungeon","_type":"Dungeon","g":[{"itemID":184518},{"itemID":184515},{"itemID":184516},{"itemID":184517}],"lvl":[56],"questID":62371},{"isDaily":1,"questID":62382},{"isDaily":1,"questID":62400},{"g":[{"itemID":183744}],"questID":62407},{"isDaily":1,"questID":62417},{"g":[{"itemID":178880},{"itemID":178877},{"itemID":178883},{"itemID":177699}],"questID":62441},{"g":[{"itemID":176921}],"questID":62442},{"g":[{"itemID":176832}],"questID":62443},{"g":[{"itemID":176922}],"questID":62444},{"g":[{"itemID":176922},{"itemID":176921},{"itemID":176832}],"questID":62445},{"g":[{"itemID":183704}],"questID":62447},{"g":[{"itemID":176922},{"itemID":176921},{"itemID":176832}],"questID":62449},{"g":[{"itemID":176922},{"itemID":176921},{"itemID":176832}],"questID":62450},{"g":[{"itemID":176922},{"itemID":176921},{"itemID":176832}],"questID":62452},{"isDaily":1,"questID":62453},{"_category":"Dungeon","g":[{"itemID":184519}],"questID":62456},{"_category":"Dungeon","questID":62458},{"isDaily":1,"questID":62459},{"_type":"Group","questID":62461},{"isDaily":1,"questID":62465},{"isDaily":1,"questID":62466},{"_category":"Path of Ascension","questID":62477},{"questID":62483,"lvl":[60],"_category":"Path of Ascension"},{"_category":"Path of Ascension","questID":62486},{"g":[{"itemID":184315}],"questID":62569},{"g":[{"itemID":183805}],"questID":62603},{"lvl":[54],"questID":62605},{"isDaily":1,"questID":62606},{"isDaily":1,"questID":62607},{"isDaily":1,"questID":62608},{"isDaily":1,"questID":62610},{"isDaily":1,"questID":62611},{"isDaily":1,"questID":62614},{"isDaily":1,"questID":62615},{"g":[{"itemID":183806}],"questID":62625},{"g":[{"itemID":184315}],"questID":62631},{"g":[{"itemID":184316}],"questID":62632},{"g":[{"itemID":184316}],"questID":62633},{"g":[{"itemID":184316}],"questID":62634},{"g":[{"itemID":184316}],"questID":62635},{"g":[{"itemID":184316}],"questID":62636},{"g":[{"itemID":184316}],"questID":62638},{"_area":"Torghast, Tower of the Damned","lvl":[60],"questID":62700},{"lvl":[51],"questID":62714},{"lvl":[51],"questID":62715},{"lvl":[51],"questID":62718},{"lvl":[60],"questID":62719},{"_area":"Maldraxxus","questID":62738},{"_area":"Ardenweald","questID":62739},{"_area":"Revendreth","questID":62740},{"_area":"Maldraxxus","questID":62761},{"_area":"Ardenweald","questID":62776},{"_area":"Revendreth","questID":62779},{"lvl":[54],"questID":62785},{"questID":62789,"lvl":[60],"_category":"Covenant Sanctum"},{"questID":62790,"lvl":[60],"_category":"Covenant Sanctum"},{"questID":62791,"lvl":[60],"_category":"Covenant Sanctum"},{"questID":62792,"lvl":[60],"_category":"Covenant Sanctum"},{"questID":62793,"lvl":[60],"_category":"Covenant Sanctum","g":[{"itemID":178156},{"itemID":177053},{"itemID":174292}]},{"questID":62794,"lvl":[60],"_category":"Covenant Sanctum"},{"questID":62795,"lvl":[60],"_category":"Covenant Sanctum"},{"questID":62796,"lvl":[60],"_category":"Covenant Sanctum"},{"questID":62797,"lvl":[60],"_area":"The Maw"},{"questID":62798,"lvl":[60],"_area":"The Maw"},{"questID":62799,"lvl":[60],"_area":"The Maw"},{"questID":62800,"lvl":[60],"_area":"The Maw"},{"questID":62801,"lvl":[50],"_area":"Oribos"},{"questID":62804,"lvl":[60],"_area":"Maldraxxus","g":[{"itemID":184156}]},{"questID":62807,"lvl":[57],"_area":"Ardenweald"},{"questID":62832,"lvl":[60],"_category":"Covenant Sanctum"},{"questID":62833,"lvl":[60],"_category":"Covenant Sanctum"},{"questID":62834,"lvl":[60],"_category":"Covenant Sanctum"},{"questID":62835,"lvl":[60],"_category":"Covenant Sanctum"},{"questID":62836,"lvl":[60],"_area":"The Maw"},{"questID":62837,"lvl":[60],"_area":"The Maw"},{"questID":62839,"lvl":[60],"_category":"Covenant Sanctum"},{"questID":62840,"lvl":[60],"_category":"Covenant Sanctum"},{"questID":62843,"lvl":[60],"_category":"Covenant Sanctum"},{"questID":62844,"lvl":[60],"_category":"Covenant Sanctum"},{"questID":62845,"lvl":[60],"_category":"Covenant Sanctum","g":[{"itemID":182272},{"itemID":182263},{"itemID":182281},{"itemID":182254}]},{"questID":62846,"lvl":[60],"_category":"Covenant Sanctum"},{"questID":62848,"lvl":[60],"_category":"Covenant Sanctum"},{"questID":62849,"lvl":[60],"_area":"Revendreth"},{"questID":62850,"lvl":[60],"_area":"Bastion"},{"questID":62851,"lvl":[60],"_area":"Maldraxxus"},{"questID":62852,"lvl":[60],"_area":"Revendreth"},{"questID":62855,"lvl":[60],"_area":"The Maw"},{"questID":62856,"lvl":[60],"_category":"Covenant Sanctum"},{"questID":62857,"lvl":[60],"_category":"Covenant Sanctum"},{"questID":62858,"lvl":[60],"_category":"Covenant Sanctum"},{"questID":62859,"lvl":[60],"_category":"Covenant Sanctum"},{"questID":62860,"lvl":[60],"_category":"Covenant Sanctum"},{"questID":62861,"lvl":[60],"_category":"Covenant Sanctum"},{"questID":62862,"lvl":[60],"_category":"Covenant Sanctum"},{"questID":62863,"lvl":[60],"_category":"Covenant Sanctum"},{"questID":62864,"lvl":[60],"_category":"Covenant Sanctum"},{"questID":62865,"lvl":[60],"_category":"Covenant Sanctum"},{"questID":62866,"lvl":[60],"_category":"Covenant Sanctum"},{"questID":62867,"lvl":[60],"_category":"Covenant Sanctum"},{"questID":62868,"lvl":[60],"_category":"Covenant Sanctum"},{"questID":62869,"lvl":[60],"_category":"Covenant Sanctum"},{"questID":62870,"lvl":[60],"_area":"The Maw"},{"questID":62882,"lvl":[55],"_area":"The Maw"},{"questID":62883,"lvl":[60],"_category":"Covenant Sanctum"},{"questID":62884,"lvl":[60],"_category":"Covenant Sanctum"},{"questID":62886,"lvl":[60],"_category":"Covenant Sanctum"},{"questID":62890,"lvl":[60],"_category":"Covenant Sanctum"},{"questID":62891,"lvl":[60],"_category":"Covenant Sanctum"},{"questID":62892,"lvl":[60],"_category":"Covenant Sanctum"},{"questID":62893,"lvl":[60],"_category":"Covenant Sanctum"},{"questID":62894,"lvl":[60],"_category":"Covenant Sanctum"},{"questID":62895,"lvl":[60],"_area":"Bastion"},{"questID":62896,"lvl":[60],"_area":"Bastion"},{"questID":62897,"lvl":[60],"_category":"Covenant Sanctum"},{"questID":62898,"lvl":[60],"_category":"Covenant Sanctum"},{"questID":62899,"lvl":[60],"_category":"Covenant Sanctum"},{"questID":62900,"lvl":[60],"_category":"Covenant Sanctum"},{"questID":62902,"lvl":[60],"_category":"Covenant Sanctum"},{"questID":62903,"lvl":[60],"_category":"Covenant Sanctum"},{"questID":62904,"lvl":[60],"_category":"Covenant Sanctum"},{"questID":62905,"lvl":[60],"_category":"Covenant Sanctum"},{"questID":62910,"lvl":[60],"r":2,"_category":"World PvP"},{"questID":62911,"lvl":[60],"r":1,"_category":"World PvP"},{"questID":62914,"lvl":[60],"_category":"Covenant Sanctum"},{"questID":62915,"lvl":[60],"_category":"Covenant Sanctum"},{"questID":62916,"lvl":[60],"_category":"Covenant Sanctum"},{"questID":62917,"lvl":[60],"_category":"Covenant Sanctum"},{"questID":62918,"lvl":[60],"_category":"Covenant Sanctum"},{"questID":62919,"lvl":[60],"_category":"Covenant Sanctum"},{"questID":62920,"lvl":[60],"_category":"Covenant Sanctum"},{"questID":62921,"lvl":[60],"_category":"Covenant Sanctum"},{"questID":62928,"lvl":[60],"_category":"Path of Ascension"},{"questID":62932,"lvl":[60],"_area":"The Maw","g":[{"itemID":184758}]},{"questID":62935,"lvl":[60],"_area":"The Maw"},{"questID":62938,"lvl":[60],"_area":"The Maw"},{"questID":62951,"lvl":[60],"_category":"Path of Ascension","g":[{"itemID":184812}]},{"questID":62952,"lvl":[60],"_category":"Path of Ascension","g":[{"itemID":184812}]},{"questID":62953,"lvl":[60],"_category":"Path of Ascension","g":[{"itemID":184812}]},{"questID":62954,"lvl":[60],"_category":"Path of Ascension","g":[{"itemID":184812}]},{"questID":62966,"lvl":[60],"_area":"The Maw"},{"questID":62967,"lvl":[60],"_area":"The Maw","_type":"Legendary"},{"questID":62969,"lvl":[60],"_area":"The Maw"},{"questID":62970,"lvl":[60],"_category":"Path of Ascension"},{"questID":62971,"lvl":[60],"_category":"Path of Ascension"},{"questID":62976,"lvl":[60],"_category":"Path of Ascension"},{"questID":62981,"lvl":[60],"_category":"Path of Ascension"},{"questID":62984,"lvl":[60],"_category":"Path of Ascension"},{"questID":62985,"lvl":[60],"_area":"Revendreth"},{"questID":62986,"lvl":[60],"_category":"Path of Ascension"},{"questID":62987,"lvl":[60],"_area":"Revendreth"},{"questID":62995,"lvl":[60],"_category":"Path of Ascension"},{"questID":62996,"lvl":[60],"_category":"Path of Ascension"},{"questID":62997,"lvl":[60],"_category":"Path of Ascension"},{"questID":62998,"lvl":[60],"_category":"Path of Ascension"},{"questID":62999,"lvl":[60]},{"questID":63000,"lvl":[60],"_category":"Path of Ascension"},{"questID":63002,"lvl":[60],"_category":"Covenant Sanctum"},{"questID":63003,"lvl":[60],"_category":"Covenant Sanctum"},{"questID":63006,"lvl":[60],"_area":"Ardenweald"},{"questID":63008,"lvl":[60],"_category":"Covenant Sanctum"},{"questID":63022,"lvl":[60],"_area":"The Maw"},{"questID":63024,"lvl":[60],"_category":"Covenant Sanctum"},{"questID":63025,"lvl":[60],"_category":"Covenant Sanctum"},{"questID":63026,"lvl":[60],"_category":"Covenant Sanctum"},{"questID":63027,"lvl":[60],"_category":"Covenant Sanctum"},{"questID":63029,"lvl":[60],"_area":"The Maw"},{"questID":63030,"lvl":[60],"_area":"The Maw"},{"questID":63031,"isDaily":1,"lvl":[60],"_area":"The Maw"},{"questID":63032,"lvl":[60],"_area":"The Maw"},{"questID":63033,"lvl":[60],"_area":"The Maw"},{"questID":63034,"lvl":[50],"_area":"Bastion"},{"questID":63035,"lvl":[50],"_area":"Maldraxxus"},{"questID":63036,"lvl":[50],"_area":"Ardenweald"},{"questID":63037,"lvl":[50],"_area":"Revendreth"},{"questID":63038,"isDaily":1,"lvl":[60],"_area":"The Maw","_type":"Group"},{"questID":63039,"isDaily":1,"lvl":[60],"_area":"The Maw"},{"questID":63040,"isDaily":1,"lvl":[60],"_area":"The Maw","_type":"Group"},{"questID":63041,"lvl":[60],"g":[{"itemID":184522}]},{"questID":63043,"isDaily":1,"lvl":[60],"_area":"The Maw"},{"questID":63045,"isDaily":1,"lvl":[60],"_area":"The Maw","_type":"Group"},{"questID":63046,"lvl":[60],"_area":"Ardenweald"},{"questID":63047,"isDaily":1,"lvl":[60],"_area":"The Maw"},{"questID":63050,"isDaily":1,"lvl":[60],"_area":"The Maw"},{"questID":63051,"lvl":[60],"_area":"The Maw"},{"questID":63052,"lvl":[60],"_category":"Covenant Sanctum"},{"questID":63053,"lvl":[60],"_category":"Covenant Sanctum"},{"questID":63054,"lvl":[60],"_category":"Covenant Sanctum"},{"questID":63055,"lvl":[60],"_category":"Covenant Sanctum"},{"questID":63056,"lvl":[60],"_area":"Revendreth"},{"questID":63057,"lvl":[60],"_category":"Covenant Sanctum"},{"questID":63058,"lvl":[60],"_category":"Covenant Sanctum"},{"questID":63059,"lvl":[60],"_category":"Covenant Sanctum"},{"questID":63060,"lvl":[60],"_area":"The Maw"},{"questID":63061,"lvl":[60],"_category":"Covenant Sanctum"},{"questID":63062,"isDaily":1,"lvl":[60],"_area":"The Maw"},{"questID":63063,"lvl":[60],"_area":"Revendreth"},{"questID":63064,"lvl":[60],"_area":"Revendreth"},{"questID":63065,"lvl":[60],"_area":"Revendreth"},{"questID":63066,"lvl":[60],"_area":"Revendreth"},{"questID":63067,"lvl":[60],"_category":"Covenant Sanctum"},{"questID":63068,"lvl":[52],"_area":"Bastion"},{"questID":63069,"isDaily":1,"lvl":[60],"_area":"The Maw"},{"questID":63072,"isDaily":1,"lvl":[60],"_area":"The Maw"},{"questID":63073,"lvl":[60],"_category":"Covenant Sanctum"},{"questID":63100,"isDaily":1,"lvl":[60],"_area":"The Maw"},{"questID":63101,"lvl":[60],"_category":"Covenant Sanctum"},{"questID":63132,"lvl":[60],"_area":"The Maw"},{"questID":63133,"lvl":[60],"_area":"The Maw"},{"questID":63134,"lvl":[60],"_area":"The Maw"},{"questID":63135,"lvl":[60],"_area":"The Maw"},{"questID":63136,"lvl":[60],"_area":"The Maw"},{"questID":63137,"lvl":[60],"_area":"The Maw"},{"questID":63140,"lvl":[60],"_area":"The Maw"},{"questID":63142,"lvl":[60],"_area":"The Maw"},{"questID":63145,"lvl":[60],"_area":"The Maw"},{"questID":63152,"lvl":[60],"_area":"The Maw"},{"questID":63153,"lvl":[60],"_area":"The Maw"},{"questID":63154,"lvl":[60],"_area":"The Maw"},{"questID":63155,"lvl":[60],"_area":"The Maw"},{"questID":63156,"lvl":[60],"_area":"The Maw"},{"questID":63157,"lvl":[60],"_area":"The Maw"},{"questID":63158,"lvl":[60],"_area":"The Maw"},{"questID":63159,"lvl":[60],"_area":"The Maw"},{"questID":63160,"lvl":[60],"_area":"The Maw"},{"questID":63161,"lvl":[60],"_area":"The Maw"},{"questID":63162,"lvl":[60],"_area":"The Maw"},{"questID":63163,"lvl":[60],"_area":"The Maw"},{"questID":63164,"lvl":[60],"_area":"The Maw"},{"questID":63166,"isDaily":1,"lvl":[60],"_area":"The Maw"},{"questID":63168,"lvl":[60],"_category":"Path of Ascension","g":[{"itemID":184812}]},{"questID":63169,"lvl":[60],"_category":"Path of Ascension","g":[{"itemID":184812}]},{"questID":63170,"lvl":[60],"_category":"Path of Ascension","g":[{"itemID":184812}]},{"questID":63171,"lvl":[60],"_category":"Path of Ascension","g":[{"itemID":184812}]},{"questID":63172,"lvl":[60],"_category":"Path of Ascension","g":[{"itemID":184812}]},{"questID":63173,"lvl":[60],"_category":"Path of Ascension","g":[{"itemID":184812}]},{"questID":63174,"lvl":[60],"_category":"Path of Ascension","g":[{"itemID":184812}]},{"questID":63175,"lvl":[60],"_category":"Path of Ascension","g":[{"itemID":184812}]},{"questID":63176,"lvl":[60],"_category":"Path of Ascension","g":[{"itemID":184812}]},{"questID":63179,"isDaily":1,"lvl":[60],"_area":"The Maw"},{"questID":63181,"lvl":[60],"_category":"Path of Ascension","g":[{"itemID":184811}]},{"questID":63182,"lvl":[60],"_category":"Path of Ascension","g":[{"itemID":184811}]},{"questID":63184,"lvl":[60],"_category":"Path of Ascension","g":[{"itemID":184811}]},{"questID":63185,"lvl":[60],"_category":"Path of Ascension","g":[{"itemID":184811}]},{"questID":63186,"lvl":[60],"_category":"Path of Ascension","g":[{"itemID":184811}]},{"questID":63187,"lvl":[60],"_category":"Path of Ascension","g":[{"itemID":184811}]},{"questID":63188,"lvl":[60],"_category":"Path of Ascension","g":[{"itemID":184811}]},{"questID":63189,"lvl":[60],"_category":"Path of Ascension","g":[{"itemID":184811}]},{"questID":63190,"lvl":[60],"_category":"Path of Ascension","g":[{"itemID":184811}]},{"questID":63191,"lvl":[60],"_category":"Path of Ascension","g":[{"itemID":184811}]},{"questID":63192,"lvl":[60],"_category":"Path of Ascension","g":[{"itemID":184811}]},{"questID":63206,"isDaily":1,"lvl":[60],"_area":"The Maw"},{"questID":63208,"lvl":[50],"_area":"Oribos"},{"questID":63209,"lvl":[50],"_area":"Oribos"},{"questID":63210,"lvl":[50],"_area":"Oribos"},{"questID":63211,"lvl":[60],"_category":"Covenant Sanctum"},{"questID":63212,"lvl":[60],"_category":"Covenant Sanctum"},{"questID":63213,"isDaily":1,"lvl":[60],"_area":"Revendreth","g":[{"itemID":184627}]},{"questID":63214,"lvl":[60],"_category":"Covenant Sanctum"},{"questID":63215,"lvl":[60],"_category":"Covenant Sanctum"},{"questID":63340,"lvl":[60],"_category":"Covenant Sanctum"},{"questID":63341,"lvl":[60],"_category":"Covenant Sanctum"},{"questID":63342,"lvl":[60],"_category":"Covenant Sanctum"},{"questID":63343,"lvl":[60],"_category":"Covenant Sanctum"},{"questID":63344,"lvl":[60],"_category":"Covenant Sanctum"},{"questID":63345,"lvl":[60],"_category":"Covenant Sanctum"},{"questID":63346,"lvl":[60],"_category":"Covenant Sanctum"},{"questID":63347,"lvl":[60],"_category":"Covenant Sanctum"}]}